alea/CEtAPI.dll
alea/CEtAPIx64.dll
alea/EtApi.dll
alea/__init__.py
alea/alea.py
python_alea-0.0.9.dist-info/DESCRIPTION.rst
python_alea-0.0.9.dist-info/METADATA
python_alea-0.0.9.dist-info/RECORD
python_alea-0.0.9.dist-info/WHEEL
python_alea-0.0.9.dist-info/metadata.json
python_alea-0.0.9.dist-info/top_level.txt
