Metadata-Version: 2.0
Name: python-alea
Version: 0.0.9
Summary: Python wrapper for the IntelliGaze API by Alea Technologies
Home-page: https://github.com/esdalmaijer/PyAlea
Author: Edwin Dalmaijer
Author-email: edwin.dalmaijer@gmail.com
License: UNKNOWN
Platform: UNKNOWN
Classifier: Intended Audience :: Science/Research
Classifier: Topic :: Scientific/Engineering
Classifier: Programming Language :: Python :: 2
Classifier: License :: OSI Approved :: Apache Software License
Classifier: Operating System :: Microsoft :: Windows
